kafka_rpc
