Metadata-Version: 2.1
Name: kafka-rpc
Version: 1.0.7
Summary: RPC protocol based on kafka
Home-page: https://github.com/zylo117/kafka-rpc
Author: Carl Cheung
License: Apache License 2.0
Platform: UNKNOWN
Classifier: Development Status :: 5 - Production/Stable
Classifier: Intended Audience :: Developers
Classifier: Natural Language :: English
Classifier: License :: OSI Approved :: MIT License
Classifier: Programming Language :: Python
Classifier: Programming Language :: Python :: 3
